tap_geotab/__init__.py
tap_geotab/client.py
tap_geotab/schemas/device_status_info.json
tap_geotab/schemas/devices.json
tap_geotab/schemas/status_data.json
tap_geotab/streams.py
tap_geotab/tap.py
tap_geotab-1.0.4.dist-info/LICENSE
tap_geotab-1.0.4.dist-info/METADATA
tap_geotab-1.0.4.dist-info/WHEEL
tap_geotab-1.0.4.dist-info/entry_points.txt
tap_geotab-1.0.4.dist-info/RECORD
