Metadata-Version: 2.1
Name: tap-geotab
Version: 1.0.4
Summary: `tap-geotab` is a Singer tap for Geotab, built with the Meltano Singer SDK.
License: Apache-2.0
Keywords: ELT,Geotab
Author: Hidde Stokvis
Author-email: hidde@trunkrs.nl
Requires-Python: >=3.8,<4
Classifier: License :: OSI Approved :: Apache Software License
Classifier: Programming Language :: Python :: 3
Classifier: Programming Language :: Python :: 3.8
Classifier: Programming Language :: Python :: 3.9
Classifier: Programming Language :: Python :: 3.10
Classifier: Programming Language :: Python :: 3.11
Provides-Extra: s3
Requires-Dist: fs-s3fs (>=1.1.1,<1.2.0) ; extra == "s3"
Requires-Dist: mygeotab (>=0.8.8,<0.9.0)
Requires-Dist: singer-sdk (>=0.34.0,<0.35.0)
